anylabeling/__init__.py
anylabeling/app.py
anylabeling/app_info.py
anylabeling/config.py
anylabeling/utils.py
anylabeling/configs/__init__.py
anylabeling/configs/models.yaml
anylabeling/configs/xanylabeling_config.yaml
anylabeling/configs/__pycache__/__init__.cpython-310.pyc
anylabeling/configs/__pycache__/__init__.cpython-312.pyc
anylabeling/configs/__pycache__/__init__.cpython-38.pyc
anylabeling/configs/__pycache__/__init__.cpython-39.pyc
anylabeling/configs/auto_labeling/__init__.py
anylabeling/configs/auto_labeling/ch_chinese_cht_en_japan_ppocr_v5.yaml
anylabeling/configs/auto_labeling/ch_ppocr_v4.yaml
anylabeling/configs/auto_labeling/clrnet_tusimple_r18.yaml
anylabeling/configs/auto_labeling/damo_yolo_l.yaml
anylabeling/configs/auto_labeling/damo_yolo_m.yaml
anylabeling/configs/auto_labeling/damo_yolo_s.yaml
anylabeling/configs/auto_labeling/damo_yolo_t.yaml
anylabeling/configs/auto_labeling/deimv2_dinov3_m_coco.yaml
anylabeling/configs/auto_labeling/deimv2_dinov3_s_coco.yaml
anylabeling/configs/auto_labeling/deimv2_hgnetv2_n_coco.yaml
anylabeling/configs/auto_labeling/depth_anything_v2_vit_b.yaml
anylabeling/configs/auto_labeling/depth_anything_v2_vit_l.yaml
anylabeling/configs/auto_labeling/depth_anything_v2_vit_s.yaml
anylabeling/configs/auto_labeling/depth_anything_vit_b.yaml
anylabeling/configs/auto_labeling/depth_anything_vit_l.yaml
anylabeling/configs/auto_labeling/depth_anything_vit_s.yaml
anylabeling/configs/auto_labeling/dfine_l_obj2coco.yaml
anylabeling/configs/auto_labeling/dfine_m_obj2coco.yaml
anylabeling/configs/auto_labeling/dfine_s_obj2coco.yaml
anylabeling/configs/auto_labeling/dfine_x_obj2coco.yaml
anylabeling/configs/auto_labeling/doclayout_yolo.yaml
anylabeling/configs/auto_labeling/edge_sam.yaml
anylabeling/configs/auto_labeling/edge_sam_with_chinese_clip.yaml
anylabeling/configs/auto_labeling/efficientvit_sam_l0_vit_h.yaml
anylabeling/configs/auto_labeling/efficientvit_sam_l1_vit_h.yaml
x_anylabeling_cvhub-3.3.5.dist-info/LICENSE
x_anylabeling_cvhub-3.3.5.dist-info/METADATA
x_anylabeling_cvhub-3.3.5.dist-info/WHEEL
x_anylabeling_cvhub-3.3.5.dist-info/entry_points.txt
x_anylabeling_cvhub-3.3.5.dist-info/top_level.txt
x_anylabeling_cvhub-3.3.5.dist-info/RECORD
