Metadata-Version: 2.2
Name: x-anylabeling-cvhub
Version: 3.3.5
Summary: Advanced Auto Labeling Solution with Added Features
Author-email: Wei Wang <cv_hub@163.com>
Maintainer-email: CVHub <cvhub.cn@gmail.com>
License: GPLv3
Project-URL: Source, https://github.com/CVHub520/X-AnyLabeling
Project-URL: Documentation, https://github.com/CVHub520/X-AnyLabeling/tree/main/docs
Project-URL: Bug Reports, https://github.com/CVHub520/X-AnyLabeling/issues
Project-URL: Changelog, https://github.com/CVHub520/X-AnyLabeling/releases
Keywords: machine-learning,deep-learning,computer-vision,multi-modal,auto-labeling,image-annotation,AI,LLM,VLM,YOLO,SAM,CLIP,Grounding-DINO,X-AnyLabeling
Classifier: Development Status :: 4 - Beta
Classifier: Intended Audience :: Developers
Classifier: Intended Audience :: Education
Classifier: Intended Audience :: Science/Research
Classifier: License :: OSI Approved :: GNU General Public License v3 (GPLv3)
Classifier: Programming Language :: Python :: 3
Classifier: Programming Language :: Python :: 3.10
Classifier: Programming Language :: Python :: 3.11
Classifier: Programming Language :: Python :: 3.12
Classifier: Topic :: Scientific/Engineering :: Artificial Intelligence
Classifier: Topic :: Scientific/Engineering :: Image Processing
Classifier: Topic :: Software Development :: Libraries :: Python Modules
Classifier: Operating System :: POSIX :: Linux
Classifier: Operating System :: MacOS
Classifier: Operating System :: Microsoft :: Windows
Requires-Python: >=3.10
License-File: LICENSE
Requires-Dist: natsort>=8.1.0
Requires-Dist: numpy<=1.26.4
Requires-Dist: pillow>=7.1.2
Requires-Dist: opencv-contrib-python-headless>=4.7.0.72
Requires-Dist: PyQt5>=5.15.7
Requires-Dist: PyQtWebEngine>=5.15.7
Requires-Dist: qimage2ndarray>=1.10.0
Requires-Dist: lapx>=0.5.5
Requires-Dist: tqdm>=4.64.0
Requires-Dist: scipy>=1.4.1
Requires-Dist: PyYAML
Requires-Dist: importlib_metadata
Requires-Dist: json_repair
Requires-Dist: jsonlines
Requires-Dist: markdown
Requires-Dist: openai
Requires-Dist: psutil
Requires-Dist: pyclipper
Requires-Dist: six
Requires-Dist: shapely
Requires-Dist: termcolor
Requires-Dist: tokenizers
Requires-Dist: requests
Provides-Extra: dev
Requires-Dist: build; extra == "dev"
Requires-Dist: black; extra == "dev"
Requires-Dist: flake8; extra == "dev"
Requires-Dist: pyinstaller; extra == "dev"
Requires-Dist: pytest; extra == "dev"
Requires-Dist: twine; extra == "dev"
Provides-Extra: cpu
Requires-Dist: onnx>=1.15.0; extra == "cpu"
Requires-Dist: onnxruntime>=1.15.0; extra == "cpu"
Provides-Extra: gpu
Requires-Dist: onnx>=1.15.0; extra == "gpu"
Requires-Dist: onnxruntime-gpu>=1.18.1; platform_system != "Darwin" and extra == "gpu"
Provides-Extra: gpu-cu11
Requires-Dist: onnx<1.16.1,>=1.15.0; extra == "gpu-cu11"
Requires-Dist: onnxruntime-gpu<1.19.0,>=1.15.0; platform_system != "Darwin" and extra == "gpu-cu11"
